segimage/__init__.py
segimage/cli/__init__.py
segimage/cli/commands/__init__.py
segimage/cli/commands/formats.py
segimage/cli/commands/info.py
segimage/cli/commands/inspect.py
segimage/cli/commands/process.py
segimage/cli/main.py
segimage/graphs/__init__.py
segimage/graphs/affinity.py
segimage/graphs/contrast4.py
segimage/graphs/grid.py
segimage/graphs/prob4.py
segimage/graphs/segments.py
segimage/graphs/superpixel_adjacency.py
segimage/pipelines/__init__.py
segimage/pipelines/graph_hedonic.py
segimage/pipelines/graph_view.py
segimage/pipelines/slico_graph.py
segimage/pipelines/slico_graph_hedonic.py
segimage/processor.py
segimage/processors/__init__.py
segimage/processors/color_cluster.py
segimage/processors/graph.py
segimage/processors/lbp.py
segimage/processors/slico.py
segimage/py.typed
segimage/utils.py
segimage-0.0.3.dist-info/WHEEL
segimage-0.0.3.dist-info/entry_points.txt
segimage-0.0.3.dist-info/METADATA
segimage-0.0.3.dist-info/RECORD
