Metadata-Version: 2.3
Name: segimage
Version: 0.0.3
Summary: Image segmentation and processing library with CLI support
Author: Lucas Lopes Felipe
Requires-Dist: scipy>=1.7.0
Requires-Dist: click>=8.0.0
Requires-Dist: pillow>=8.0.0
Requires-Dist: scikit-image>=0.20.0
Requires-Dist: hedonic>=0.0.10
Requires-Dist: pytest>=6.0.0 ; extra == 'dev'
Requires-Dist: black>=21.0.0 ; extra == 'dev'
Requires-Dist: flake8>=3.8.0 ; extra == 'dev'
Requires-Python: >=3.12
Provides-Extra: dev
